LICENSE
README.md
setup.py
gluish/__init__.py
gluish/common.py
gluish/format.py
gluish/intervals.py
gluish/parameter.py
gluish/task.py
gluish/utils.py
gluish.egg-info/PKG-INFO
gluish.egg-info/SOURCES.txt
gluish.egg-info/dependency_links.txt
gluish.egg-info/requires.txt
gluish.egg-info/top_level.txt