Metadata-Version: 2.1
Name: gluish
Version: 0.3.3
Summary: Luigi helper.
Home-page: https://github.com/miku/gluish
Author: Martin Czygan
Author-email: martin.czygan@gmail.com
License-File: LICENSE
